configurator/__init__.py
configurator/fields.py
configurator/main.py
configurator/utils.py
service_configurator-1.0.0.dist-info/LICENSE
service_configurator-1.0.0.dist-info/METADATA
service_configurator-1.0.0.dist-info/WHEEL
service_configurator-1.0.0.dist-info/top_level.txt
service_configurator-1.0.0.dist-info/RECORD
