Metadata-Version: 2.1
Name: service-configurator
Version: 1.0.0
Summary: A package for storing service config and secrets
Home-page: https://github.com/piotrekm7/service-configurator
Author: Piotr Muras
Author-email: piotrekm7@gmail.com
License: MIT
Classifier: License :: OSI Approved :: MIT License
Classifier: Intended Audience :: Developers
Classifier: Topic :: Software Development :: Libraries :: Application Frameworks
Classifier: Topic :: Software Development :: Libraries :: Python Modules
Classifier: Topic :: Software Development :: Libraries
Classifier: Topic :: Software Development
Classifier: Programming Language :: Python :: 3
Classifier: Programming Language :: Python :: 3.8
Classifier: Programming Language :: Python :: 3.9
Classifier: Programming Language :: Python :: 3.10
Requires-Python: >=3.8.1
License-File: LICENSE
Requires-Dist: pyyaml (>=6.0.0)
